W800rf32/__init__.py
W800rf32/lowlevel.py
pyw800rf32-0.5.dist-info/licenses/COPYING.txt
pyw800rf32-0.5.dist-info/METADATA
pyw800rf32-0.5.dist-info/WHEEL
pyw800rf32-0.5.dist-info/top_level.txt
pyw800rf32-0.5.dist-info/RECORD
