Metadata-Version: 2.4
Name: pyW800rf32
Version: 0.5
Summary: A library to communicate with the W800rf32 family of devices
Home-page: https://github.com/horga83/W800rf32
Author: George Farris
Author-email: George Farris <farrisg@gmsys.com>
Project-URL: Homepage, https://github.com/horga83/pyW800rf32
Project-URL: Bug Tracker, https://github.com/horga83/pyW800rf32/issues
Classifier: Programming Language :: Python :: 3
Classifier: License :: OSI Approved :: GNU Lesser General Public License v3 or later (LGPLv3+)
Classifier: Operating System :: OS Independent
Requires-Python: >=3.8
License-File: COPYING.txt
Requires-Dist: pyserial>=3.1
Dynamic: author
Dynamic: home-page
Dynamic: license-file
